speaklater.py
flaskpress_speaklater-1.3.0.dist-info/DESCRIPTION.rst
flaskpress_speaklater-1.3.0.dist-info/METADATA
flaskpress_speaklater-1.3.0.dist-info/RECORD
flaskpress_speaklater-1.3.0.dist-info/WHEEL
flaskpress_speaklater-1.3.0.dist-info/metadata.json
flaskpress_speaklater-1.3.0.dist-info/top_level.txt
