Metadata-Version: 2.0
Name: flaskpress-speaklater
Version: 1.3.0
Summary: Implements a lazy string for python for use with gettext
Home-page: http://github.com/infrascloudy/flaskpress_speaklater
Author: InfrasCloudy, @allanice001
Author-email: support@linaccess.za.net
License: UNKNOWN
Platform: UNKNOWN
Classifier: Development Status :: 5 - Production/Stable
Classifier: License :: OSI Approved :: BSD License
Classifier: Topic :: Software Development :: Internationalization
Classifier: Programming Language :: Python
